bip39validator/BIP39WordList.py
bip39validator/InitUniqResult.py
bip39validator/InvalidRemoteContent.py
bip39validator/InvalidWordList.py
bip39validator/LevDistResult.py
bip39validator/MaxLengthResult.py
bip39validator/ValidWordList.py
bip39validator/ValidationFailed.py
bip39validator/__init__.py
bip39validator/__main__.py
bip39validator/__version__.py
bip39validator/internal/__init__.py
bip39validator/internal/data_structs.py
bip39validator/internal/logging.py
bip39validator/internal/util.py
bip39validator/internal/validation_tests.py
tests/__init__.py
tests/test_bip39wordlist.py
tests/test_inituniqresult.py
tests/test_levdistresult.py
tests/test_maxlengthresult.py
tests/test_programs.py
bip39validator-1.0.7.dist-info/LICENSE
bip39validator-1.0.7.dist-info/METADATA
bip39validator-1.0.7.dist-info/WHEEL
bip39validator-1.0.7.dist-info/entry_points.txt
bip39validator-1.0.7.dist-info/top_level.txt
bip39validator-1.0.7.dist-info/RECORD
