Metadata-Version: 2.1
Name: bip39validator
Version: 1.0.7
Summary: Validator for BIP39 wordlists
Home-page: https://github.com/ZenulAbidin/bip39validator
Author: Ali Sherief
Author-email: alihsherief@linuxmail.org
License: MIT
Project-URL: Changelog, https://github.com/ZenulAbidin/bip39validator/blob/master/CHANGELOG.md
Project-URL: Issue Tracker, https://github.com/ZenulAbidin/bip39validator/issues
Platform: UNKNOWN
Classifier: Development Status :: 4 - Beta
Classifier: Intended Audience :: Developers
Classifier: License :: OSI Approved :: MIT License
Classifier: Operating System :: Unix
Classifier: Operating System :: POSIX
Classifier: Operating System :: Microsoft :: Windows
Classifier: Programming Language :: Python
Classifier: Programming Language :: Python :: 3.6
Classifier: Programming Language :: Python :: 3.7
Classifier: Programming Language :: Python :: 3.8
Classifier: Programming Language :: Python :: 3.9
Classifier: Programming Language :: Python :: Implementation :: CPython
Classifier: Topic :: Software Development :: Testing
Requires-Python: >=3.6
Requires-Dist: jellyfish
Requires-Dist: rich
Requires-Dist: requests
Requires-Dist: validators
